flagsmith/__init__.py
flagsmith/analytics.py
flagsmith/api/__init__.py
flagsmith/api/types.py
flagsmith/exceptions.py
flagsmith/flagsmith.py
flagsmith/mappers.py
flagsmith/models.py
flagsmith/offline_handlers.py
flagsmith/polling_manager.py
flagsmith/py.typed
flagsmith/streaming_manager.py
flagsmith/types.py
flagsmith/utils/__init__.py
flagsmith/utils/datetime.py
flagsmith/utils/identities.py
flagsmith/version.py
flagsmith/webhooks.py
flagsmith-5.1.1.dist-info/METADATA
flagsmith-5.1.1.dist-info/WHEEL
flagsmith-5.1.1.dist-info/licenses/LICENSE
flagsmith-5.1.1.dist-info/RECORD
