Metadata-Version: 2.4
Name: flagsmith
Version: 5.1.1
Summary: Flagsmith Python SDK
License: BSD3
License-File: LICENSE
Keywords: feature,flag,flagsmith,remote,config
Author: Flagsmith
Author-email: support@flagsmith.com
Requires-Python: >=3.9,<4
Classifier: License :: Other/Proprietary License
Classifier: Programming Language :: Python :: 3
Classifier: Programming Language :: Python :: 3.9
Classifier: Programming Language :: Python :: 3.10
Classifier: Programming Language :: Python :: 3.11
Classifier: Programming Language :: Python :: 3.12
Classifier: Programming Language :: Python :: 3.13
Classifier: Programming Language :: Python :: 3.14
Requires-Dist: flagsmith-flag-engine (>=10.0.3,<11.0.0)
Requires-Dist: iso8601 (>=2.1.0,<3.0.0) ; python_version < "3.11"
Requires-Dist: requests (>=2.32.3,<3.0.0)
Requires-Dist: requests-futures (>=1.0.1,<2.0.0)
Requires-Dist: sseclient-py (>=1.8.0,<2.0.0)
Requires-Dist: typing-extensions (>=4.15.0,<5.0.0)
Project-URL: Documentation, https://docs.flagsmith.com
